dfhist
